drf_recaptcha/__init__.py
drf_recaptcha/apps.py
drf_recaptcha/checks.py
drf_recaptcha/client.py
drf_recaptcha/constants.py
drf_recaptcha/fields.py
drf_recaptcha/validators.py
drf_recaptcha-4.0.3.dist-info/LICENSE.md
drf_recaptcha-4.0.3.dist-info/METADATA
drf_recaptcha-4.0.3.dist-info/WHEEL
drf_recaptcha-4.0.3.dist-info/RECORD
