Metadata-Version: 2.3
Name: drf-recaptcha
Version: 4.0.3
Summary: Django rest framework recaptcha field serializer
License: MIT
Keywords: django,drf,rest,django-rest-framework,reCAPTCHA,reCAPTCHA v2,reCAPTCHA v3
Author: Lev Lybin
Author-email: lev.lybin@gmail.com
Requires-Python: >=3.10
Classifier: Development Status :: 5 - Production/Stable
Classifier: Environment :: Plugins
Classifier: Environment :: Web Environment
Classifier: Framework :: Django
Classifier: Framework :: Django :: 4.2
Classifier: Framework :: Django :: 5.0
Classifier: Framework :: Django :: 5.1
Classifier: Framework :: Django :: 5.2
Classifier: Intended Audience :: Developers
Classifier: License :: OSI Approved :: MIT License
Classifier: Operating System :: OS Independent
Classifier: Programming Language :: Python
Classifier: Programming Language :: Python :: 3
Classifier: Programming Language :: Python :: 3.10
Classifier: Programming Language :: Python :: 3.11
Classifier: Programming Language :: Python :: 3.12
Classifier: Programming Language :: Python :: 3.13
Classifier: Programming Language :: Python :: 3 :: Only
Classifier: Topic :: Internet :: WWW/HTTP :: Dynamic Content
Classifier: Topic :: Security
Classifier: Topic :: Software Development :: Libraries
Requires-Dist: django (>=4.2)
Requires-Dist: django-ipware (>=5.0)
Requires-Dist: djangorestframework (>=3.14)
Project-URL: Homepage, https://github.com/llybin/drf-recaptcha
Project-URL: Repository, https://github.com/llybin/drf-recaptcha
